{
  "lisa_manifest": 1,
  "app_id": "org.lisa.notes",
  "mcp": { "transport": "unix", "activatable": false },
  "tools": [
    {
      "name": "create_note",
      "tier": "write",
      "description": "Create a note with a title and optional body",
      "input_schema": {
        "type": "object",
        "required": ["title"],
        "additionalProperties": false,
        "properties": {
          "title": { "type": "string", "maxLength": 120 },
          "body": { "type": "string", "maxLength": 4000 }
        }
      },
      "undo": { "tool": "delete_note", "map": { "id": "$result.id" } }
    },
    {
      "name": "list_notes",
      "tier": "read",
      "description": "List active notes (id, title, created), oldest first",
      "input_schema": {
        "type": "object",
        "additionalProperties": false,
        "properties": {}
      }
    },
    {
      "name": "delete_note",
      "tier": "write",
      "description": "Soft-delete a note; restorable via restore_note",
      "input_schema": {
        "type": "object",
        "required": ["id"],
        "additionalProperties": false,
        "properties": {
          "id": { "type": "integer" }
        }
      },
      "undo": { "tool": "restore_note", "map": { "id": "$input.id" } }
    },
    {
      "name": "restore_note",
      "tier": "write",
      "description": "Restore a soft-deleted note",
      "input_schema": {
        "type": "object",
        "required": ["id"],
        "additionalProperties": false,
        "properties": {
          "id": { "type": "integer" }
        }
      }
    }
  ]
}
